{"name":"BHR_Beschrijflocatie","refDomainVersions":[{"majorVersion":1,"minorVersion":0,"refCodes":[{"code":"lab","description":"Het monster is beschreven in een beschrijfruimte.","imbro":"J","imbroA":"J"},{"code":"veld","description":"Het monster is in het veld beschreven.","imbro":"J","imbroA":"J"}]},{"majorVersion":2,"minorVersion":0,"refCodes":[{"code":"lab","description":"Het monster is beschreven in een beschrijfruimte.","imbro":"J","imbroA":"J"},{"code":"veld","description":"Het monster is in het veld beschreven.","imbro":"J","imbroA":"J"}]}],"uri":"urn:bro:bhr:DescriptionLocation"}